toolbelt_requests/__init__.py
toolbelt_requests/requests_util.py
toolbelt_requests-0.0.1.dist-info/METADATA
toolbelt_requests-0.0.1.dist-info/WHEEL
toolbelt_requests-0.0.1.dist-info/top_level.txt
toolbelt_requests-0.0.1.dist-info/RECORD
