Metadata-Version: 2.1
Name: toolbelt-requests
Version: 0.0.1
Summary: Typosquatting talk example, do not use.
Home-page: https://github.com/requests/toolbelt
Author: N. Body
Author-email: dontuse@gmail.com
License: Apache
Classifier: Programming Language :: Python
Classifier: Programming Language :: Python :: 3
